{
    "お姉ちゃんはっけーーーん！！": "",
    "うわぁ！！\nちょっ……危ないでしょ佑芽ぇえ！！": "",
    "えへへ、親愛のハグ～！": "",
    "…………": "",
    "ことね、今日こそは……": "",
    "げっ……しっつれいしまぁーす！": "",
    "あっ！\n……もう、まったく困った後輩だよ。": "",
    "ごめんね、勉強に付き合わせちゃって。": "",
    "ううん、困った時はお互い様でしょ？": "",
    "ふふ、いつも頼りにしてるよ。": "",
    "左手はこうやって……ぴんっ、だよ。": "",
    "ぴ、ぴんっ！　ですのっ！？": "",
    "そう、ぴんっ！\nふふ、できてるできてる。": "",
    "へへっ、またひっかかった～♪": "",
    "す、清夏ちゃん……！": "",
    "……も、もう！　いたずらばっかり……": "",
    "いい筋肉ね！　どんなトレーニングを\nしているのかしら。": "",
    "わたしのメニューも教えるから、\nぜひ清夏のも――": "",
    "あー、あたし鍛えてないし、\nそーゆーのはダイジョブかな～。": "",
    "ふぅ～。": "",
    "わぁ～！　綺麗！\n篠澤さん、お上手ですわ！": "",
    "……ふふ。千奈も、やってみる？": "",
    "あら、また力みすぎてるみたいね。": "",
    "はわわっ！　せ、星南お姉さま……\nまさか、ご覧になって……！？": "",
    "（うぅ～……\n嬉し恥ずかしすぎますわぁ～っ！）": "",
    "んっ、んっ……ぷはー！！": "",
    "（え、一気飲み……？\nこんなマズいものをっ！？）": "",
    "（信じられない……！）": "",
    "ぽかぽかしていて……\n絶好のお昼寝スポットですね。": "",
    "ん、ぅ……すぅ……": "",
    "……ふふ。では、わたしも。": "",
    "流石ことねね。\n自分の魅せ方をよくわかってる。": "",
    "やはりあなたは、\n私のモノになるべきだわ。": "",
    "あはは……光栄ですぅ。": "",
    "お水、飲んでください。": "",
    "たすかった……いのちの恩人。": "",
    "焦らずゆっくり行きましょう": "",
    "はい、花びら取れたよ。": "",
    "……ん？　ああ、ありがとう。": "",
    "……なんてやり取りも、あと1年かぁ。": "",
    "さて、ここまでは大丈夫ですか？": "",
    "質問があったら、\nなんでも言ってください。": "",
    "先生に遠慮はいりませんからね。": "",
    "なぁに聴いてんの？　手毬ちゃーん。": "",
    "あ、ちょっ……！\n勝手に触らないで！": "",
    "どりゃっ！": "",
    "ぎゃっ！！": "",
    "えっ、もう無理なの？": "",
    "くっ……！": "",
    "まだまだ！": "",
    "はい、キメポっ！": "",
    "へ？": "",
    "あっ！　ほっ！": "",
    "ふふ、水着だと落ち着かない？": "",
    "水着、変じゃないかなって……": "",
    "すっごく可愛いよ！": "",
    "アー……アアー": "",
    "どう？　宇宙人の声。": "",
    "バカじゃないの。": "",
    "――ほら、ボクの背中に乗って。": "",
    "心配しなくて大丈夫。": "",
    "うぅ……。\n麻央センパイの背中、あったかい……。": "",
    "こうして、こう！　ですわ！": "",
    "ちなっち、さっすが～♪": "",
    "帯だけではなく、\n腰紐をきちんと締めるのがコツですの。": "",
    "なんだかことねの気配を感じるわ。": "",
    "わたあめお面でバレないはず！": "",
    "ふふ――見えてるわよ。": "",
    "今年の新入生はどう？": "",
    "ふふ、ダイヤの原石がいっぱいよ。": "",
    "それは楽しみだね。": "",
    "ことねちゃんのすすき、\nすごく立派だね！": "",
    "わ～～～～っありがとぉ！": "",
    "…………って、遊ぶかぁぁ！！": "",
    "役作り……難しいな……": "",
    "月村さんが演じるこの方は、\nとてもひねくれた方なのです。": "",
    "詳しく教えて！": "",
    "面白そうな飲み物。": "",
    "ふふ～、お目が高いわね。": "",
    "なにを混ぜたらそんな色に\nなるんだろう、ふしぎ。": "",
    "このまえ、見ちゃったんです……": "",
    "お姉ちゃんの特製ドリンクのレシピ。\nごにょごにょごにょ……": "",
    "えええ～っ！？": "",
    "こうしてうちわで扇ぐと\nまんべんなく焼けるのですわ……！": "",
    "なるほど……火の通りを\n良くするために行うのね。": "",
    "こうすることで煙の匂いがつかなくて、\n香りも良くなるんですの！": "",
    "まおっち先輩、表情固いですよー！\nもっと！　笑顔で！": "",
    "こ、こうかい？\nこういうのは不慣れでね。": "",
    "んー、でも、困り顔のまおっち先輩も、\nかわいーからよしです！": "",
    "見て、トンボがいるわ！\nなんだか懐かしいわね。": "",
    "どっちがいっぱい捕まえられるか、\n勝負よ、佑芽！": "",
    "よおおおっし！　\n負けないよ、お姉ちゃんっ！": "",
    "ふぉっふぉっふぉ～。": "",
    "よい子のもとに\nプレゼントを届けに行くぞぉ～。": "",
    "ふふっ♪\n佑芽トナカイにお任せあれっ！": "",
    "手はあごにそえて～、\n口角はキュッと！": "",
    "こ、こう……ですか？": "",
    "そーそー！\nいいじゃんいいじゃん♪": "",
    "よければ、さ。\n半分ずつにしようよ！": "",
    "そこまで言うなら仕方なく――はむ。": "",
    "目がキラッキラになっちゃって～。\n可愛いヤツだなぁ～♪": "",
    "もう少しだ、最後まで気を緩めるな！": "",
    "は、はい！　1、2、3、4――": "",
    "疲れている時ほど、\n指先まで意識するんだ！": "",
    "さっすが咲季ちゃん。完璧よ。": "",
    "ありがとうございます！\nトレーナーさんのおかげです！": "",
    "嬉しいこと言ってくれるじゃない。\nもうワンセット、いってみる？": "",
    "お腹を意識しながら、\nゆっくりと息を吸ってー、吐いてー。": "",
    "……あんまり、\nお腹触ってほしくないんですけど。": "",
    "これもレッスンですから。\n基礎は大切ですよ？": "",
    "ふふっ。隠し味は――これよ！": "",
    "す、すごい！\nチョコが虹色に光り出した――": "",
    "これが化学反応……！": "",
    "このあたりを盛ると\nほほが柔らかく見えると思います。": "",
    "なるほど……こうかしら？": "",
    "はい。\nとても可愛らしくなりましたね。": "",
    "わぁ！　すごく綺麗な音色っ♪": "",
    "葉をピンと張って。\n咥えすぎないのがコツ。": "",
    "上手く吹くの……\nむ、難しいですわ～～～！": "",
    "有村先輩、それ、\n早く外に放ってください！": "",
    "そんなに怖がらなくても……\nほら、こんなに可愛いのに。": "",
    "ふわあっ！？\n見せなくていいですからっ！": "",
    "リーリヤ！\nまだ跳べるでしょう！？": "",
    "は、はい……！　頑張ります！": "",
    "その意気よ！\nでも、負けてはあげないわ！": "",
    "ねえねえ、これ可愛くない？": "",
    "やば、めっちゃ可愛いじゃん！": "",
    "だよね～、やっぱ清夏とは趣味合うわ。": "",
    "はい、ひと口あげる！": "",
    "（……食べられんの、これ？）": "",
    "……いらない。": "",
    "（とっさに隠れちゃったけど……\nなにやってるんだろ、私……）": "",
    "（……なんだか……\n懐かしい気配がしたような……）": "",
    "（……あたたかいほうに、\n向かいましょう）": "",
    "ぜっったい、許さないから！！": "",
    "そこまで怒ることないでしょ！！": "",
    "こいつらめんどくさー……": "",
    "はい！　メイクばっちり！\nってことで遊びに行こー！": "",
    "いーえ、全然なってないわ！\nそこになおりなさい！": "",
    "やっぱりだめかクッソぉ～～～！": "",
    "ふぬぬぅ～……おねーひゃんめぇ～、": "",
    "ひょーこそ、じぇったい……": "",
    "じぇ～ったい、負けにゃいから～……": "",
    "私たち、もう3年生なんだ。": "",
    "……ああ。\n元気な新入生たちに恥じないよう、": "",
    "ボクたちも、もっと頑張らないとね。": "",
    "ふぇぇ……終わりませんわぁ～！": "",
    "大丈夫、あとちょっとだよ。": "",
    "最後まで、一緒にがんばろう？": "",
    "キミ、飲み物は大丈夫？": "",
    "あ、ありがとうございます……！": "",
    "（まるで、王子様みたい……です）": "",
    "ヤバい、リーリヤあれ見て！": "",
    "どうしたの、清夏ちゃ――": "",
    "はい、チーズ！": "",
    "今日が最後のチャンス。": "",
    "な、なんとしても成功させますわぁ～！": "",
    "んぐっ……よし、がんばろー！": "",
    "この子は？": "",
    "わたくしの宝物ですわ！\nか、かわいいでしょう？": "",
    "くまちゃんも千奈ちゃんもかわいい！": "",
    "会長、美鈴ちゃん！　遊びに来たよ！": "",
    "まあ。ふふ、今日も元気ですね。": "",
    "もう……\n生徒会室は遊び場じゃないのよ。": "",
    "（ふぅ……\nこのあたりで少し休憩を――）": "",
    "はぁっ……！　まだ、まだ……！": "",
    "……もう。": "",
    "いらっしゃいま――げっ！": "",
    "奇遇ね、ことね。": "",
    "（この人、こんなとこまでッ！！）": "",
    "まだまだ序の口、始まったばかりよ！": "",
    "私の声が聞こえないくらい、\n盛り上がってみせなさい！": "",
    "……これが、一番星……": "",
    "さあ、\n新生徒会に相応しい一枚にするわよ！": "",
    "ま、まままだ心の準備がぁ～～！！": "",
    "……ふぁぁ。": "",
    "広ちゃん確保～！": "",
    "確保された。": "",
    "秦谷さんも、\nちゃんとついてきてくださいましっ！": "",
    "……はい、観念しました。": "",
    "最後のひと箱、出発しんこー♪": "",
    "ま、待って……！\n重いから、慎重に……": "",
    "だいじょーぶ、だいじょーぶ！": "",
    "手毬っち～、\n全然お菓子食べてなくない？": "",
    "もしかして、ダイエット中～？": "",
    "ぐっ……うるさいな。": "",
    "ふふっ、このくらいお安い御用ですよ。": "",
    "どんどん先生を頼ってください。": "",
    "きみはわたしの、生徒なんですから。": "",
    "あっ、秋の味覚フェアなんですね！　\nちょうどお腹がすいていますし。": "",
    "栗ご飯弁当と、おにぎりと……\nスイーツもいっちゃいましょうか！": "",
    "ふふふ……こんなお昼ご飯も、\nたまにはいいでしょう！": "",
    "まりちゃん、風邪を引きますよ。": "",
    "わ、わかってる……！": "",
    "調子狂うな……もう……": "",
    "あっ！　麻央先輩、虹ですよ～": "",
    "ああ、本当だ。": "",
    "ふふ、掃除のご褒美……かな？": "",
    "あ、水たまりはっけーん！": "",
    "ちょっと佑芽！": "",
    "やめなさーい！": "",
    "あー……\nぜんっぜん、わっかんね～": "",
    "こらことね！\nそうじゃないって言ってるでしょ！？": "",
    "ごほうび……とんかつ……すぅ……": "",
    "わたくしたち、こんなところまで\n来られたのですね……！": "",
    "ふふ……つかれた……": "",
    "登頂記念のご飯だー！\nいっただっきまーす！": "",
    "プール掃除なんて\nダルいと思ってたけどさ。": "",
    "リーリヤと一緒なら楽しいね！": "",
    "……うん。わたしも楽しい♪": "",
    "さあっ！　皆様！\n辛く苦しいレッスンの後は――": "",
    "バカンスを楽しむ時間ですわ～～～♪": "",
    "お～～～～～～～～～～～～っ！": "",
    "一時休戦しませんか？": "",
    "ふん、私を言い\nくるめられると思ってるの？": "",
    "……懐かしいですね、このやり取り。": "",
    "お～し、挟み撃ちするぞ～！": "",
    "任せてことね": "",
    "こんなときだけ息ぴったりね！": "",
    "あっちにあるのはなんですの！": "",
    "ふふっ♪　千奈ちゃん。\nそんなに急いだらはぐれちゃうよ？": "",
    "大丈夫ですの！\nお姉さまと手を繋いでいますから！": "",
    "任せて。火をつけてあげる。": "",
    "わっ、ありがとうございます……！": "",
    "ふふっ、手持ち花火って、\n楽しいですね。": "",
    "燕ちゃんが心配ですか？": "",
    "そ、そんなことはないわ。\n思い悩んでいただけよ。": "",
    "私がスカウトしてしまった……\n問題児たちのことをね。": "",
    "洗濯が終わるまで、\n残り時間はどれくらいかな。": "",
    "まだまだじゃないかな。": "",
    "じゃあお茶、おかわり淹れるね！": "",
    "その本、おもしろい？": "",
    "ドキドキするよ～": "",
    "わたしも読んでみようかしら": "",
    "手毬っち、これつけてみてよ！": "",
    "ぜったいに嫌。ちょ、勝手に――": "",
    "へへっ、めっちゃ似合うじゃん！\n可愛い～！": "",
    "う～ん♪　涼しくなってきましたわね！": "",
    "秋といえば芸術、読書、食欲の秋！\nさっそく秋を食べに行きましょう！": "",
    "千奈と一緒だと、楽しいことばかり。\nふふ。いつもありがとう。": "",
    "リハーサルの準備、できました。": "",
    "新入生への訓示は、少し緊張するわね。": "",
    "会長でも緊張するんですか？\n意外です。": "",
    "あら、ことねじゃない。\n先に行かせてもらうわね。": "",
    "……は、速すぎませんかぁ～！？": "",
    "フフ。ついてこられるかしら？": "",
    "ふふっ、そろそろ頃合いかな。\nなかなかタイミングが難しくてね。": "",
    "……いい匂い。\nワクワク、します……。": "",
    "ん、こっちはもういけそうだね。\nどうぞ、リーリヤ。": "",
    "美鈴ちゃん！\nあっちも見てみようよ！": "",
    "ふふふ、いいですよ。": "",
    "こらこら、慌てないの。": "",
    "雪が降ってきたね～。": "",
    "バスが来るまで、もう少しかな？\nちょっと寒くなってきたね。": "",
    "はい、そんなリーリヤには、\nマフラーのおすそ分けだよ！": "",
    "へへっ、引っかかった～♪\nこれで、あたしの独走状態……！": "",
    "待ちなさ～い！\nこの程度で、わたしは負けないわよ！": "",
    "げっ！？　速すぎでしょっ！？": "",
    "お疲れ手毬っち～。スポドリ飲む？": "",
    "リーリヤが、\n次はこのパートやりたいって。": "",
    "うひーっ。ごめ～ん、遅れちった～！": "",
    "わたくしたちもいつかはきっと――": "",
    "大きなステージで、\nこの曲を歌いたいよねっ！": "",
    "ふふ……まだまだ先は長い。": "",
    "（今度こそ、絶対に――）": "",
    "（自分のものにしてみせる）": "",
    "（この歌を一番\n　歌いこなせるのは――私だ！）": "",
    "お姉ちゃん型チョコとかどうですか！": "",
    "すっごく可愛いっ！\n食べるのもったいないね♪": "",
    "えへへ～♡\n喜んでくれるといいな～！": "",
    "ぎょ、行列ですわ～！": "",
    "ふふ、こんなに集まってくれる\nなんて、嬉しいわ。": "",
    "わたくしの順番、もうすぐ……\nん～！　ドキドキしますわぁ～！": "",
    "う、うぅ……怖い……": "",
    "ええと……ひとりで立てますか？": "",
    "ま、待って！\n私の傍から離れないで！": "",
    "今日は思いっきり遊ぼう！": "",
    "はげしすぎますわ～～～～！？": "",
    "おお……佑芽、わたしにもやって。": "",
    "手伝ってくれてありがとう、有村さん。\nこれから一緒に頑張ろうね！": "",
    "ああ。あの桜の花がまた咲く頃には、": "",
    "ボクたちも、きっと――": "",
    "つ、次は絶対に勝つ！": "",
    "フフ、受けて立つわ。": "",
    "ふたりとも、そろそろ休もう？": "",
    "本気でいくよ……咲季ちゃん。": "",
    "かかってきなさいリーリヤ。": "",
    "相手にとって不足なしよ！": "",
    "せっかくだし、\nここで写真撮らない？": "",
    "お、いいじゃん！\n入学記念だね！": "",
    "笑って笑って――はい、チーズ♪": ""
}